{"cameraMode":{"drawMode":0,"name":"Shaded","section":"Shading Mode"},"sceneLighting":true,"audioPlay":false,"sceneViewState":{"m_AlwaysRefresh":false,"showFog":true,"showSkybox":true,"showFlares":true,"showImageEffects":true,"showParticleSystems":true,"showVisualEffectGraphs":true,"m_FxEnabled":true},"in2DMode":false,"pivot":{"x":-0.09741934388875961,"y":3.638531446456909,"z":-9.850386619567871},"rotation":{"x":0.08833783864974976,"y":0.3576776385307312,"z":-0.03400639817118645,"w":0.9290538430213928},"size":3.1912224292755129,"orthographic":false}